firefox_cookie/__init__.py
firefox_cookie/__main__.py
firefox_cookie-0.0.3.dist-info/METADATA
firefox_cookie-0.0.3.dist-info/WHEEL
firefox_cookie-0.0.3.dist-info/entry_points.txt
firefox_cookie-0.0.3.dist-info/top_level.txt
firefox_cookie-0.0.3.dist-info/RECORD
